yango_tech_grocery_client/__init__.py
yango_tech_grocery_client/base_client.py
yango_tech_grocery_client/cli.py
yango_tech_grocery_client/client.py
yango_tech_grocery_client/client_prices.py
yango_tech_grocery_client/client_third_party_logistics.py
yango_tech_grocery_client/constants.py
yango_tech_grocery_client/endpoints.py
yango_tech_grocery_client/exceptions.py
yango_tech_grocery_client/py.typed
yango_tech_grocery_client/rate_limiter.py
yango_tech_grocery_client/schema.py
yango_tech_grocery_client/tests/test_rate_limiter.py
yango_tech_grocery_client/utils.py
yango_tech_grocery_client-1.2.0.dist-info/METADATA
yango_tech_grocery_client-1.2.0.dist-info/WHEEL
yango_tech_grocery_client-1.2.0.dist-info/entry_points.txt
yango_tech_grocery_client-1.2.0.dist-info/licenses/LICENSE
yango_tech_grocery_client-1.2.0.dist-info/RECORD
