Metadata-Version: 2.4
Name: yango-tech-grocery-client
Version: 1.2.0
Summary: A Python client library for interacting with the Yango Tech Grocery API
License: MIT
License-File: LICENSE
Keywords: yango,grocery,api,client,delivery,ecommerce
Requires-Python: >=3.10,<4.0
Classifier: Development Status :: 4 - Beta
Classifier: Intended Audience :: Developers
Classifier: License :: OSI Approved :: MIT License
Classifier: Operating System :: OS Independent
Classifier: Programming Language :: Python :: 3
Classifier: Programming Language :: Python :: 3.10
Classifier: Programming Language :: Python :: 3.11
Classifier: Programming Language :: Python :: 3.12
Classifier: Programming Language :: Python :: 3.13
Classifier: Programming Language :: Python :: 3.14
Classifier: Topic :: Software Development :: Libraries :: Python Modules
Requires-Dist: aiohttp (>=3.12.0,<4.0.0)
Requires-Dist: dacite (>=1.9.0,<2.0.0)
Requires-Dist: yarl (>=1.8.0,<2.0.0)
Project-URL: Bug Tracker, https://github.com/yango-tech/yango-tech-grocery-client/issues
Project-URL: Documentation, https://github.com/yango-tech/yango-tech-grocery-client#readme
Project-URL: Homepage, https://github.com/yango-tech/yango-tech-grocery-client
Project-URL: Repository, https://github.com/yango-tech/yango-tech-grocery-client
